{"extensions": {"python.details": {"document_names": {"description": "DESCRIPTION.rst"}}}, "extras": [], "generator": "bdist_wheel (0.29.0)", "metadata_version": "2.0", "name": "odoo8-addons-oca-geospatial", "run_requires": [{"requires": ["odoo8-addon-base-geoengine", "odoo8-addon-base-geoengine-demo", "odoo8-addon-geoengine-base-geolocalize", "odoo8-addon-geoengine-geoname-geocoder", "odoo8-addon-geoengine-partner", "odoo8-addon-geoengine-project", "odoo8-addon-geoengine-sale"]}], "summary": "Meta package for OCA geospatial Odoo addons", "version": "8.0.20160911"}