{"classifiers": ["Programming Language :: Python :: 2.7", "Framework :: Odoo"], "extensions": {"python.details": {"document_names": {"description": "DESCRIPTION.rst"}}}, "extras": [], "generator": "bdist_wheel (0.29.0)", "metadata_version": "2.0", "name": "odoo10-addons-oca-event", "run_requires": [{"requires": ["odoo10-addon-event-contact", "odoo10-addon-event-mail", "odoo10-addon-event-project", "odoo10-addon-event-registration-mass-mailing", "odoo10-addon-event-registration-multi-qty", "odoo10-addon-event-session", "odoo10-addon-partner-event", "odoo10-addon-website-event-excerpt-img", "odoo10-addon-website-event-filter-selector", "odoo10-addon-website-event-share", "odoo10-addon-website-event-type-description"]}], "summary": "Meta package for OCA event Odoo addons", "version": "10.0.20171222"}