{"classifiers": ["Programming Language :: Python :: 2.7", "Framework :: Odoo"], "extensions": {"python.details": {"document_names": {"description": "DESCRIPTION.rst"}}}, "extras": [], "generator": "bdist_wheel (0.29.0)", "metadata_version": "2.0", "name": "odoo8-addons-oca-mis-builder", "run_requires": [{"requires": ["odoo8-addon-mis-builder", "odoo8-addon-mis-builder-analytic-filter", "odoo8-addon-mis-builder-demo"]}], "summary": "Meta package for OCA mis-builder Odoo addons", "version": "8.0.20171017"}